classic/db_pool/__init__.py
classic/db_pool/exceptions.py
classic/db_pool/pool.py
classic/db_pool/poolvalidators.py
classic_db_pool-1.1.1.dist-info/LICENSE.txt
classic_db_pool-1.1.1.dist-info/METADATA
classic_db_pool-1.1.1.dist-info/WHEEL
classic_db_pool-1.1.1.dist-info/top_level.txt
classic_db_pool-1.1.1.dist-info/RECORD
