Metadata-Version: 2.1
Name: classic-db-pool
Version: 1.1.1
Summary: Provides connections pool for work with database
Home-page: https://github.com/variasov/classic-db-pool
Author: Sergei Variasov, Oliver Cope
Author-email: variasov@gmail.com
Classifier: Programming Language :: Python :: 3.10
Classifier: License :: OSI Approved :: MIT License
Classifier: Operating System :: OS Independent
Classifier: Development Status :: 4 - Beta
Requires-Python: >=3.10
License-File: LICENSE.txt
Provides-Extra: dev
Requires-Dist: pytest~=7.4.4; extra == "dev"
Requires-Dist: pymssql==2.3.1; extra == "dev"
